README.md
setup.py
yzs/__init__.py
yzs/django_extend/__init__.py
yzs/django_extend/base_choice.py
yzs/django_extend/base_model.py
yzs/django_extend/base_test_case.py
yzs/django_extend/image_upload.py
yzs/tastypie_extend/__init__.py
yzs/tastypie_extend/base_resource.py
yzs/tastypie_extend/response_code.py
yzs_work.egg-info/PKG-INFO
yzs_work.egg-info/SOURCES.txt
yzs_work.egg-info/dependency_links.txt
yzs_work.egg-info/requires.txt
yzs_work.egg-info/top_level.txt