Metadata-Version: 1.1
Name: yzs-work
Version: 0.1.34
Summary: yzs work environment
Home-page: https://github.com/wplct/yzs-work
Author: wplct
Author-email: wplct1@gmail.com
License: Anti-996-License
Keywords: yzs work environment
Platform: UNKNOWN
Classifier: Intended Audience :: Developers
Classifier: Topic :: Software Development :: Build Tools
Classifier: Programming Language :: Python :: 3.7
